pyeqsolver-1.0.1.dist-info/licenses/LICENCE.txt
pyeqsovler/__init__.py
pyeqsovler/adjoint.py
pyeqsovler/determinant.py
pyeqsovler/linear_equations_solver.py
pyeqsovler/matrixerror.py
pyeqsovler/matrices/__init__.py
pyeqsovler/matrices/matrices2x2.py
pyeqsovler/matrices/matrices3x3.py
pyeqsolver-1.0.1.dist-info/METADATA
pyeqsolver-1.0.1.dist-info/WHEEL
pyeqsolver-1.0.1.dist-info/top_level.txt
pyeqsolver-1.0.1.dist-info/RECORD
