Metadata-Version: 2.4
Name: pyeqsolver
Version: 1.0.1
Summary: A Python package for solving linear equations and performing 2x2 and 3x3 matrix operations
Home-page: https://github.com/Hammail-Riaz/pyeqsolver
Author: Hammail Riaz
Author-email: Hammail Riaz <hammailriaz.dev@gmail.com>
License: MIT
Project-URL: Homepage, https://github.com/Hammail-Riaz/pyeqsolver
Project-URL: Documentation, https://github.com/Hammail-Riaz/pyeqsolver#readme
Project-URL: Repository, https://github.com/Hammail-Riaz/pyeqsolver
Project-URL: Bug Tracker, https://github.com/Hammail-Riaz/pyeqsolver/issues
Keywords: matrix,linear-equations,mathematics,algebra,solver
Classifier: Development Status :: 5 - Production/Stable
Classifier: Intended Audience :: Developers
Classifier: Intended Audience :: Education
Classifier: License :: OSI Approved :: MIT License
Classifier: Programming Language :: Python :: 3
Classifier: Topic :: Scientific/Engineering :: Mathematics
Requires-Python: >=3.8
License-File: LICENCE.txt
Dynamic: author
Dynamic: home-page
Dynamic: license-file
Dynamic: requires-python
